crowd_vision/__init__.py
crowd_vision/tracker.py
crowd_vision-0.1.2.dist-info/METADATA
crowd_vision-0.1.2.dist-info/WHEEL
crowd_vision-0.1.2.dist-info/top_level.txt
crowd_vision-0.1.2.dist-info/RECORD
