Metadata-Version: 2.1
Name: crowd-vision
Version: 0.1.2
Summary: An advanced library for crowd detection, tracking, and analysis in videos.
Home-page: https://github.com/yourusername/crowd_vision
Author: Shobhit Shah
Author-email: shobhitchamp21@gmail.com
Classifier: Programming Language :: Python :: 3
Classifier: License :: OSI Approved :: MIT License
Classifier: Operating System :: OS Independent
Classifier: Topic :: Scientific/Engineering :: Image Recognition
Classifier: Topic :: Scientific/Engineering :: Artificial Intelligence
Requires-Python: >=3.8
Requires-Dist: numpy
Requires-Dist: scipy
Requires-Dist: scikit-learn
Requires-Dist: torch
Requires-Dist: torchvision
Requires-Dist: opencv-python>=4.5
